cattbl/__init__.py
cattbl/base_classes.py
cattbl/eventlossbeta.py
cattbl/yeareventallocloss.py
cattbl/yeareventloss.py
cattbl/yearloss.py
cattbl-0.3.1.dist-info/LICENSE
cattbl-0.3.1.dist-info/METADATA
cattbl-0.3.1.dist-info/WHEEL
cattbl-0.3.1.dist-info/top_level.txt
cattbl-0.3.1.dist-info/RECORD
