Metadata-Version: 2.1
Name: cattbl
Version: 0.3.1
Summary: Working with various loss tables used for CAT modelling
Home-page: https://github.com/iwbailey/cattbl
Author: Iain Bailey
Author-email: Iain Bailey <iainbailey@gmail.com>
License: MIT License        
Project-URL: Homepage, https://github.com/iwbailey/cattbl
Classifier: Programming Language :: Python :: 3
Classifier: License :: OSI Approved :: MIT License
Classifier: Operating System :: OS Independent
Requires-Python: >=3.7
License-File: LICENSE
Requires-Dist: pandas (>=1.4.2)
Requires-Dist: numpy (>=1.22.3)
Requires-Dist: matplotlib (>=3.5.2)
Requires-Dist: scipy (>=1.8.1)
